digipigi/__init__.py
digipigi/digipigi.py
digipigi-0.2.0.dist-info/METADATA
digipigi-0.2.0.dist-info/WHEEL
digipigi-0.2.0.dist-info/top_level.txt
digipigi-0.2.0.dist-info/RECORD
