Metadata-Version: 2.2
Name: digipigi
Version: 0.2.0
Summary: API to use the digipigi
Home-page: https://gitlab.phys.ethz.ch/cmtqo-projects/delicate/digipigi.git
Author: Sebastian Huber
Author-email: huberse@phys.ethz.ch
Requires-Python: >=3.6
Requires-Dist: numpy>=1.18.0
Dynamic: author
Dynamic: author-email
Dynamic: home-page
Dynamic: requires-dist
Dynamic: requires-python
Dynamic: summary
